kindlepy/__init__.py
kindlepy/__main__.py
kindlepy/src/__init__.py
kindlepy/src/config.py
kindlepy/src/mail.py
kindlepy/src/util.py
kindlepy-1.0.0.dist-info/DESCRIPTION.rst
kindlepy-1.0.0.dist-info/METADATA
kindlepy-1.0.0.dist-info/RECORD
kindlepy-1.0.0.dist-info/WHEEL
kindlepy-1.0.0.dist-info/entry_points.txt
kindlepy-1.0.0.dist-info/metadata.json
kindlepy-1.0.0.dist-info/top_level.txt
